yamldoc/__init__.py
yamldoc/models.py
yamldoc/tests.py
yamldoc/management/__init__.py
yamldoc/management/misc.py
yamldoc/util/__init__.py
yamldoc/util/file.py
yamldoc/util/markup.py
yamldoc/util/misc.py
yamldoc/util/placeholder.py
yamldoc/util/resolution.py
yamldoc/util/traverse.py
django_yamldoc-2.0.0.dist-info/LICENSE
django_yamldoc-2.0.0.dist-info/METADATA
django_yamldoc-2.0.0.dist-info/WHEEL
django_yamldoc-2.0.0.dist-info/top_level.txt
django_yamldoc-2.0.0.dist-info/RECORD
