Metadata-Version: 2.1
Name: django-yamldoc
Version: 2.0.0
Summary: Quoins for static sites
Home-page: https://github.com/veikman/django-yamldoc
Author: Viktor Eikman
Author-email: viktor.eikman@gmail.com
License: GPL-3.0-only
Platform: UNKNOWN
Classifier: Development Status :: 5 - Production/Stable
Classifier: Framework :: Django :: 3.0
Classifier: Framework :: Django :: 3.1
Classifier: Intended Audience :: Developers
Classifier: Intended Audience :: System Administrators
Classifier: License :: OSI Approved :: GNU General Public License v3 (GPLv3)
Classifier: Operating System :: OS Independent
Classifier: Programming Language :: Python :: 3
Classifier: Topic :: Database
Classifier: Topic :: Software Development :: Libraries :: Python Modules
Classifier: Topic :: Software Development :: Version Control
Classifier: Topic :: Text Editors
Classifier: Topic :: Text Processing :: Markup :: Markdown
Requires-Python: >=3.8
License-File: LICENSE
Requires-Dist: PyYaml
Requires-Dist: markdown (<3.3)
Requires-Dist: ovid
Requires-Dist: pyaml
Requires-Dist: unidecode
Requires-Dist: yamlwrap
